spotware_connect/__init__.py
spotware_connect/client.py
spotware_connect/protobuf.py
spotware_connect/protocol.py
spotware_connect/messages/OpenApiCommonMessages_pb2.py
spotware_connect/messages/OpenApiCommonModelMessages_pb2.py
spotware_connect/messages/OpenApiMessages_pb2.py
spotware_connect/messages/OpenApiModelMessages_pb2.py
spotware_connect/messages/__init__.py
spotware_connect-0.1.2.dist-info/AUTHORS.rst
spotware_connect-0.1.2.dist-info/LICENSE
spotware_connect-0.1.2.dist-info/METADATA
spotware_connect-0.1.2.dist-info/WHEEL
spotware_connect-0.1.2.dist-info/entry_points.txt
spotware_connect-0.1.2.dist-info/top_level.txt
spotware_connect-0.1.2.dist-info/RECORD
