Metadata-Version: 2.1
Name: spotware-connect
Version: 0.1.2
Summary: A python client wraper for Spotware Open API 2.0
Home-page: https://github.com/marcus-santos/spotware_connect
Author: Marcus Santos
Author-email: marcus@marcus-santos.com
License: GNU General Public License v3
Keywords: spotware openapi2
Platform: UNKNOWN
Classifier: Development Status :: 4 - Beta
Classifier: Intended Audience :: Developers
Classifier: License :: OSI Approved :: GNU General Public License v3 (GPLv3)
Classifier: Natural Language :: English
Classifier: Framework :: Twisted
Classifier: Programming Language :: Python :: 3.6
Classifier: Programming Language :: Python :: 3.7
Classifier: Programming Language :: Python :: 3.8
Requires-Dist: protobuf
Requires-Dist: twisted
Requires-Dist: pyopenssl
Requires-Dist: service-identity
